{
  "order": [
    "05.jpg",
    "06.jpg",
    "04.jpg"
  ],
  "dict": {
    "06.jpg": {
      "type": "photo",
      "width": 2698,
      "height": 1799,
      "path": "./photos/Dark/06.jpg",
      "min_path": "./photos/Dark/06.min.jpg"
    },
    "05.jpg": {
      "type": "photo",
      "width": 3198,
      "height": 1798,
      "path": "./photos/Dark/05.jpg",
      "min_path": "./photos/Dark/05.min.jpg"
    },
    "04.jpg": {
      "type": "photo",
      "width": 3198,
      "height": 1798,
      "path": "./photos/Dark/04.jpg",
      "min_path": "./photos/Dark/04.min.jpg"
    }
  }
}